ec2rdp/__init__.py
ec2rdp/ec2rdp.py
ec2rdp-1.0.1.data/scripts/ec2rdp
ec2rdp-1.0.1.dist-info/DESCRIPTION.rst
ec2rdp-1.0.1.dist-info/METADATA
ec2rdp-1.0.1.dist-info/RECORD
ec2rdp-1.0.1.dist-info/WHEEL
ec2rdp-1.0.1.dist-info/metadata.json
ec2rdp-1.0.1.dist-info/top_level.txt
