Metadata-Version: 2.0
Name: ec2rdp
Version: 1.0.1
Summary: Automatically populate rdp file from ec2 instance and put the password in the clipboard
Home-page: UNKNOWN
Author: JTV Softwares
Author-email: jtvsoftwares@gmail.com
License: UNKNOWN
Platform: UNKNOWN
Classifier: Programming Language :: Python :: 2.7
Classifier: Programming Language :: Python :: 3.5
Classifier: Programming Language :: Python :: 3.6
Classifier: License :: OSI Approved :: MIT License
Classifier: Operating System :: OS Independent
Classifier: Topic :: Utilities
Classifier: Development Status :: 4 - Beta
Requires-Dist: future
Requires-Dist: configparser
Requires-Dist: boto3
Requires-Dist: pycrypto
Requires-Dist: pyperclip
